docx2pdf/__init__.py
docx2pdf/convert.jxa
docx2pdf-0.1.6.dist-info/entry_points.txt
docx2pdf-0.1.6.dist-info/LICENSE
docx2pdf-0.1.6.dist-info/WHEEL
docx2pdf-0.1.6.dist-info/METADATA
docx2pdf-0.1.6.dist-info/RECORD
