Metadata-Version: 2.1
Name: docx2pdf
Version: 0.1.6
Summary: Convert docx to pdf on Windows or macOS directly using Microsoft Word (must be installed).
Home-page: https://github.com/AlJohri/docx2pdf
License: MIT
Author: Al Johri
Author-email: al.johri@gmail.com
Requires-Python: >=3.5,<4.0
Classifier: Environment :: MacOS X
Classifier: Environment :: Win32 (MS Windows)
Classifier: License :: OSI Approved :: MIT License
Classifier: Operating System :: MacOS
Classifier: Operating System :: Microsoft :: Windows
Classifier: Programming Language :: Python :: 3
Classifier: Programming Language :: Python :: 3.5
Classifier: Programming Language :: Python :: 3.6
Classifier: Programming Language :: Python :: 3.7
Classifier: Programming Language :: Python :: 3.8
Classifier: Topic :: Office/Business :: Office Suites
Classifier: Topic :: Software Development :: Libraries
Requires-Dist: appscript (>=1.1.0,<2.0.0); sys_platform == "darwin"
Requires-Dist: importlib_metadata (>=1.3.0,<2.0.0); python_version < "3.8"
Requires-Dist: pywin32 (>=227,<228); sys_platform == "win32"
Requires-Dist: tqdm (>=4.41.0,<5.0.0)
Project-URL: Repository, https://github.com/AlJohri/docx2pdf
